setup.py
apibuilder/__init__.py
apibuilder/common.py
apibuilder/server.py
apibuilder.egg-info/PKG-INFO
apibuilder.egg-info/SOURCES.txt
apibuilder.egg-info/dependency_links.txt
apibuilder.egg-info/requires.txt
apibuilder.egg-info/top_level.txt
apibuilder/client/__init__.py
apibuilder/client/connection.py
apibuilder/client/document.py
apibuilder/client/properties.py