Metadata-Version: 1.0
Name: apibuilder
Version: 0.1.0
Summary: Library for building simple REST APIs and clients
Home-page: http://github.com/MIT-CityFARM/apibuilder
Author: Douglas Chambers
Author-email: leonchambers@mit.edu
License: UNKNOWN
Platform: UNKNOWN
